LICENSE.txt
MANIFEST.in
README.md
config.ini
logging.ini
setup.cfg
setup.py
ccmarket/__init__.py
ccmarket/base_listener.py
ccmarket/base_market_ws.py
ccmarket/config.py
ccmarket/const.py
ccmarket/main.py
ccmarket/market_ws_listener.py
ccmarket.egg-info/PKG-INFO
ccmarket.egg-info/SOURCES.txt
ccmarket.egg-info/dependency_links.txt
ccmarket.egg-info/entry_points.txt
ccmarket.egg-info/requires.txt
ccmarket.egg-info/top_level.txt
ccmarket/common/__init__.py
ccmarket/common/timer.py
ccmarket/exchanges/__init__.py
ccmarket/exchanges/binance/__init__.py
ccmarket/exchanges/binance/const.py
ccmarket/exchanges/binance/market_ws.py
ccmarket/exchanges/bitfinex/__init__.py
ccmarket/exchanges/bitfinex/const.py
ccmarket/exchanges/bitfinex/market_ws.py
ccmarket/exchanges/bitstamp/__init__.py
ccmarket/exchanges/bitstamp/const.py
ccmarket/exchanges/bitstamp/market_ws.py
ccmarket/exchanges/coinbase/__init__.py
ccmarket/exchanges/coinbase/const.py
ccmarket/exchanges/coinbase/market_ws.py
ccmarket/exchanges/huobi/__init__.py
ccmarket/exchanges/huobi/const.py
ccmarket/exchanges/huobi/market_ws.py
ccmarket/exchanges/kraken/__init__.py
ccmarket/exchanges/kraken/const.py
ccmarket/exchanges/kraken/market_ws.py
ccmarket/exchanges/okex/__init__.py
ccmarket/exchanges/okex/const.py
ccmarket/exchanges/okex/market_ws.py
ccmarket/listeners/__init__.py
ccmarket/listeners/file_listener.py
ccmarket/listeners/redis_listener.py
ccmarket/listeners/status_listener.py